supplyforge/__init__.py
supplyforge/create_pommes_craft_model.py
supplyforge/result_process.py
supplyforge/utils.py
supplyforge/fetch/__init__.py
supplyforge/fetch/crossborder_flows.py
supplyforge/fetch/day_ahead_prices.py
supplyforge/fetch/eraa_study.py
supplyforge/fetch/generation.py
supplyforge/fetch/hydro_storage.py
supplyforge/fetch/installed_capacity.py
supplyforge/fetch/net_transfer_capacities.py
supplyforge/fetch/unavailability.py
supplyforge/process/__init__.py
supplyforge/process/availability.py
supplyforge/process/capacity_factor.py
supplyforge/process/eraa_capacity_factor.py
supplyforge/process/hydro_inflow.py
supplyforge/process/upload_results.py
supplyforge-0.1.5.dist-info/licenses/LICENSE.md
supplyforge-0.1.5.dist-info/METADATA
supplyforge-0.1.5.dist-info/WHEEL
supplyforge-0.1.5.dist-info/top_level.txt
supplyforge-0.1.5.dist-info/RECORD
