Metadata-Version: 2.4
Name: supplyforge
Version: 0.1.5
Summary: A Snakemake workflow to generate country-level electricity supply datasets.
Author-email: Yassine Abdelouadoud <yassine.abdelouadoud@minesparis.psl.eu>
Project-URL: Homepage, https://git.persee.minesparis.psl.eu/energy-alternatives/supplyforge
Project-URL: Bug Tracker, https://git.persee.minesparis.psl.eu/energy-alternatives/supplyforge/-/issues
Classifier: Programming Language :: Python :: 3
Classifier: Operating System :: OS Independent
Requires-Python: >=3.8
License-File: LICENSE.md
Requires-Dist: pandas
Requires-Dist: polars
Requires-Dist: pyarrow
Requires-Dist: entsoe-py
Requires-Dist: pommes_craft
Requires-Dist: fastexcel
Requires-Dist: python-dotenv
Requires-Dist: platformdirs
Requires-Dist: plotly
Dynamic: license-file
